wet_net/__init__.py
wet_net/config/__init__.py
wet_net/config/best_configs.yaml
wet_net/config/tri_task.py
wet_net/data/__init__.py
wet_net/data/datasets.py
wet_net/data/preprocess.py
wet_net/eval/__init__.py
wet_net/eval/metrics.py
wet_net/eval/predictions.py
wet_net/mnist_demo/__init__.py
wet_net/mnist_demo/classifier.py
wet_net/mnist_demo/transforms.py
wet_net/models/__init__.py
wet_net/models/blocks.py
wet_net/models/vib.py
wet_net/models/wetnet.py
wet_net/pipelines/__init__.py
wet_net/pipelines/tri_task.py
wet_net/scripts/__init__.py
wet_net/scripts/evaluate.py
wet_net/scripts/hf_util.py
wet_net/scripts/pre_process.py
wet_net/scripts/train.py
wet_net/scripts/visualize.py
wet_net/scripts/wet_net.py
wet_net/training/__init__.py
wet_net/training/fusion.py
wet_net/training/loops.py
wet_net/training/utils.py
wet_net-0.4.0b3.dist-info/licenses/LICENSE
wet_net-0.4.0b3.dist-info/WHEEL
wet_net-0.4.0b3.dist-info/entry_points.txt
wet_net-0.4.0b3.dist-info/METADATA
wet_net-0.4.0b3.dist-info/RECORD
