Metadata-Version: 2.4
Name: wet-net
Version: 0.4.0b3
Summary: WetNet helps Aigües de Barcelona (Barcelona Water Company) predict anomalous water consumption, using machine learning.
Author: Antonio Lobo Santos, Zachary Parent, Bruno Sánchez Gómez
Author-email: Antonio Lobo Santos <antonio.lobo@iiia.csic.es>, Zachary Parent <zachparent@duck.com>, Bruno Sánchez Gómez <brunosangom@gmail.com>
License-Expression: MIT
License-File: LICENSE
Classifier: Programming Language :: Python :: 3
Classifier: Operating System :: OS Independent
Requires-Dist: huggingface-hub>=1.2.1
Requires-Dist: matplotlib>=3.10.7
Requires-Dist: numpy>=2.3.3
Requires-Dist: pandas>=2.3.2
Requires-Dist: plotly>=6.4.0
Requires-Dist: torch>=2.9.1
Requires-Dist: pyarrow>=22.0.0
Requires-Dist: requests>=2.28.1
Requires-Dist: safetensors>=0.7.0
Requires-Dist: typer>=0.19.2
Requires-Dist: umap-learn>=0.5.7
Requires-Dist: rich>=13.9.2
Requires-Dist: pyyaml>=6.0.2
Requires-Dist: seaborn>=0.13.2
Requires-Dist: torch ; extra == 'cpu'
Requires-Dist: torch ; extra == 'gpu'
Requires-Python: >=3.11
Project-URL: Homepage, https://github.com/ZachParent/wet-net
Provides-Extra: cpu
Provides-Extra: gpu
